MANIFEST.in
README.rst
pyjolokia.py
runtests.py
setup.py
tests.py
pyjolokia.egg-info/PKG-INFO
pyjolokia.egg-info/SOURCES.txt
pyjolokia.egg-info/dependency_links.txt
pyjolokia.egg-info/top_level.txt