Metadata-Version: 1.0
Name: pyjolokia
Version: 0.3.0
Summary: Pure Python based Jolokia client
Home-page: https://github.com/cwood/pyjolokia
Author: Colin Wood
Author-email: cwood06@gmail.com
License: Apache License Version 2.0
Download-URL: http://github.com/cwood/sshed/tarball/master
Keywords: jolokia,jmx
Platform: UNKNOWN
Classifier: Development Status :: 4 - Beta
Classifier: Programming Language :: Python :: 2.6
Classifier: Programming Language :: Python :: 2.7
Classifier: Programming Language :: Python :: 3.2
Classifier: Programming Language :: Python :: 3.3
Classifier: Topic :: Software Development :: Libraries :: Java Libraries
